Metadata-Version: 2.1
Name: wowool-nlp-client
Version: 0.0.7
Summary: The Wowool NLP Client
Home-page: https://www.wowool.com/
Author: Wowool
Author-email: info@wowool.com
Requires-Python: >=3.11
Requires-Dist: requests
